{
  "timestamp": "2025-11-18T00:30:39.719Z",
  "states": [
    {
      "name": "California",
      "code": "CA",
      "topTopic": "sheikh hasina",
      "category": "Law and Government",
      "trendingScore": 100,
      "topics": [
        {
          "name": "sheikh hasina",
          "relevanceScore": 100,
          "category": "Law and Government",
          "searchVolume": "2K+",
          "started": "13h ago",
          "percentageIncrease": "500%"
        },
        {
          "name": "lindsey halligan",
          "relevanceScore": 95,
          "category": "Law and Government",
          "searchVolume": "1K+",
          "started": "5h ago",
          "percentageIncrease": "400%"
        },
        {
          "name": "no tax on overtime",
          "relevanceScore": 95,
          "category": "Law and Government",
          "searchVolume": "100+",
          "started": "2h ago",
          "percentageIncrease": "200%"
        },
        {
          "name": "afscme",
          "relevanceScore": 95,
          "category": "Law and Government",
          "searchVolume": "100+",
          "started": "7h ago",
          "percentageIncrease": "200%"
        },
        {
          "name": "tekashi",
          "relevanceScore": 95,
          "category": "Law and Government",
          "searchVolume": "100+",
          "started": "6h ago",
          "percentageIncrease": "200%"
        },
        {
          "name": "kash patel",
          "relevanceScore": 90,
          "category": "Law and Government",
          "searchVolume": "100+",
          "started": "2h ago",
          "percentageIncrease": "100%"
        }
      ]
    },
    {
      "name": "Arizona",
      "code": "AZ",
      "topTopic": "oj simpson",
      "category": "Law and Government",
      "trendingScore": 95,
      "topics": [
        {
          "name": "oj simpson",
          "relevanceScore": 95,
          "category": "Law and Government",
          "searchVolume": "100+",
          "started": "10h ago",
          "percentageIncrease": "200%"
        }
      ]
    },
    {
      "name": "Florida",
      "code": "FL",
      "topTopic": "sheikh hasina",
      "category": "Law and Government",
      "trendingScore": 95,
      "topics": [
        {
          "name": "sheikh hasina",
          "relevanceScore": 95,
          "category": "Law and Government",
          "searchVolume": "1K+",
          "started": "11h ago",
          "percentageIncrease": "300%"
        },
        {
          "name": "ny post",
          "relevanceScore": 85,
          "category": "Law and Government",
          "searchVolume": "100+",
          "started": "13h ago",
          "percentageIncrease": "75%"
        }
      ]
    },
    {
      "name": "Georgia",
      "code": "GA",
      "topTopic": "sheikh hasina",
      "category": "Law and Government",
      "trendingScore": 95,
      "topics": [
        {
          "name": "sheikh hasina",
          "relevanceScore": 95,
          "category": "Law and Government",
          "searchVolume": "100+",
          "started": "7h ago",
          "percentageIncrease": "400%"
        }
      ]
    },
    {
      "name": "Illinois",
      "code": "IL",
      "topTopic": "maria pappas",
      "category": "Law and Government",
      "trendingScore": 100,
      "topics": [
        {
          "name": "maria pappas",
          "relevanceScore": 100,
          "category": "Law and Government",
          "searchVolume": "500+",
          "started": "2h ago",
          "percentageIncrease": "1000%"
        },
        {
          "name": "sheikh hasina",
          "relevanceScore": 100,
          "category": "Law and Government",
          "searchVolume": "500+",
          "started": "10h ago",
          "percentageIncrease": "600%"
        },
        {
          "name": "oj simpson death",
          "relevanceScore": 95,
          "category": "Law and Government",
          "searchVolume": "100+",
          "started": "40 minutes ago",
          "percentageIncrease": "400%"
        },
        {
          "name": "kylie toberman",
          "relevanceScore": 95,
          "category": "Law and Government",
          "searchVolume": "100+",
          "started": "1h ago",
          "percentageIncrease": "400%"
        },
        {
          "name": "fema",
          "relevanceScore": 95,
          "category": "Law and Government",
          "searchVolume": "100+",
          "started": "4h ago",
          "percentageIncrease": "400%"
        }
      ]
    },
    {
      "name": "Indiana",
      "code": "IN",
      "topTopic": "curt andersen",
      "category": "Law and Government",
      "trendingScore": 100,
      "topics": [
        {
          "name": "curt andersen",
          "relevanceScore": 100,
          "category": "Law and Government",
          "searchVolume": "2K+",
          "started": "4h ago",
          "trendBreakdown": "voluntary",
          "percentageIncrease": "1000%"
        }
      ]
    },
    {
      "name": "Maryland",
      "code": "MD",
      "topTopic": "portugal",
      "category": "Law and Government",
      "trendingScore": 100,
      "topics": [
        {
          "name": "portugal",
          "relevanceScore": 100,
          "category": "Law and Government",
          "searchVolume": "500+",
          "started": "21h ago",
          "percentageIncrease": "800%"
        }
      ]
    },
    {
      "name": "Michigan",
      "code": "MI",
      "topTopic": "prime",
      "category": "Law and Government",
      "trendingScore": 100,
      "topics": [
        {
          "name": "prime",
          "relevanceScore": 100,
          "category": "Law and Government",
          "searchVolume": "75K+",
          "started": "10h ago",
          "percentageIncrease": "1000%"
        },
        {
          "name": "sheikh hasina",
          "relevanceScore": 100,
          "category": "Law and Government",
          "searchVolume": "100+",
          "started": "9h ago",
          "percentageIncrease": "900%"
        }
      ]
    },
    {
      "name": "Massachusetts",
      "code": "MA",
      "topTopic": "oj simpson death",
      "category": "Law and Government",
      "trendingScore": 100,
      "topics": [
        {
          "name": "oj simpson death",
          "relevanceScore": 100,
          "category": "Law and Government",
          "searchVolume": "500+",
          "started": "40 minutes ago",
          "trendBreakdown": "simpsonoj",
          "percentageIncrease": "1000%"
        },
        {
          "name": "sheikh hasina",
          "relevanceScore": 100,
          "category": "Law and Government",
          "searchVolume": "500+",
          "started": "10h ago",
          "percentageIncrease": "700%"
        },
        {
          "name": "lindsey halligan",
          "relevanceScore": 100,
          "category": "Law and Government",
          "searchVolume": "100+",
          "started": "4h ago",
          "percentageIncrease": "700%"
        }
      ]
    },
    {
      "name": "Missouri",
      "code": "MO",
      "topTopic": "chief",
      "category": "Law and Government",
      "trendingScore": 80,
      "topics": [
        {
          "name": "chief",
          "relevanceScore": 80,
          "category": "Law and Government",
          "searchVolume": "100+",
          "started": "3h ago",
          "percentageIncrease": "600%"
        }
      ]
    },
    {
      "name": "New Jersey",
      "code": "NJ",
      "topTopic": "oj simpson death",
      "category": "Law and Government",
      "trendingScore": 100,
      "topics": [
        {
          "name": "oj simpson death",
          "relevanceScore": 100,
          "category": "Law and Government",
          "searchVolume": "500+",
          "started": "40 minutes ago",
          "trendBreakdown": "simpsonoj",
          "percentageIncrease": "500%"
        },
        {
          "name": "sheikh hasina",
          "relevanceScore": 100,
          "category": "Law and Government",
          "searchVolume": "500+",
          "started": "11h ago",
          "percentageIncrease": "600%"
        }
      ]
    },
    {
      "name": "North Carolina",
      "code": "NC",
      "topTopic": "why are flags at half mast today",
      "category": "Law and Government",
      "trendingScore": 95,
      "topics": [
        {
          "name": "why are flags at half mast today",
          "relevanceScore": 95,
          "category": "Law and Government",
          "searchVolume": "500+",
          "started": "18h ago",
          "percentageIncrease": "200%"
        },
        {
          "name": "oj simpson",
          "relevanceScore": 95,
          "category": "Law and Government",
          "searchVolume": "100+",
          "started": "12h ago",
          "percentageIncrease": "200%"
        },
        {
          "name": "ice",
          "relevanceScore": 90,
          "category": "Law and Government",
          "searchVolume": "100+",
          "started": "16h ago",
          "percentageIncrease": "100%"
        }
      ]
    },
    {
      "name": "New York",
      "code": "NY",
      "topTopic": "sheikh hasina",
      "category": "Law and Government",
      "trendingScore": 100,
      "topics": [
        {
          "name": "sheikh hasina",
          "relevanceScore": 100,
          "category": "Law and Government",
          "searchVolume": "2K+",
          "started": "12h ago",
          "trendBreakdown": "prime",
          "percentageIncrease": "900%"
        },
        {
          "name": "lindsey halligan",
          "relevanceScore": 100,
          "category": "Law and Government",
          "searchVolume": "500+",
          "started": "5h ago",
          "percentageIncrease": "700%"
        },
        {
          "name": "wktv",
          "relevanceScore": 90,
          "category": "Law and Government",
          "searchVolume": "100+",
          "started": "13h ago",
          "percentageIncrease": "100%"
        }
      ]
    },
    {
      "name": "Ohio",
      "code": "OH",
      "topTopic": "oj simpson death",
      "category": "Law and Government",
      "trendingScore": 100,
      "topics": [
        {
          "name": "oj simpson death",
          "relevanceScore": 100,
          "category": "Law and Government",
          "searchVolume": "500+",
          "started": "40 minutes ago",
          "trendBreakdown": "simpsonoj",
          "percentageIncrease": "800%"
        }
      ]
    },
    {
      "name": "Oregon",
      "code": "OR",
      "topTopic": "devon dobek update",
      "category": "Law and Government",
      "trendingScore": 95,
      "topics": [
        {
          "name": "devon dobek update",
          "relevanceScore": 95,
          "category": "Law and Government",
          "searchVolume": "200+",
          "started": "21h ago",
          "trendBreakdown": "devon",
          "percentageIncrease": "300%"
        }
      ]
    },
    {
      "name": "Pennsylvania",
      "code": "PA",
      "topTopic": "sheikh hasina",
      "category": "Law and Government",
      "trendingScore": 100,
      "topics": [
        {
          "name": "sheikh hasina",
          "relevanceScore": 100,
          "category": "Law and Government",
          "searchVolume": "500+",
          "started": "10h ago",
          "percentageIncrease": "600%"
        }
      ]
    },
    {
      "name": "South Carolina",
      "code": "SC",
      "topTopic": "amber alert charlotte nc",
      "category": "Law and Government",
      "trendingScore": 100,
      "topics": [
        {
          "name": "amber alert charlotte nc",
          "relevanceScore": 100,
          "category": "Law and Government",
          "searchVolume": "200+",
          "started": "17h ago",
          "percentageIncrease": "1000%"
        }
      ]
    },
    {
      "name": "Tennessee",
      "code": "TN",
      "topTopic": "wolfchase galleria",
      "category": "Law and Government",
      "trendingScore": 100,
      "topics": [
        {
          "name": "wolfchase galleria",
          "relevanceScore": 100,
          "category": "Law and Government",
          "searchVolume": "2K+",
          "started": "3h ago",
          "trendBreakdown": "wolfchase",
          "percentageIncrease": "1000%"
        },
        {
          "name": "wreg",
          "relevanceScore": 95,
          "category": "Law and Government",
          "searchVolume": "100+",
          "started": "3h ago",
          "percentageIncrease": "400%"
        },
        {
          "name": "knoxville weather",
          "relevanceScore": 85,
          "category": "Law and Government",
          "searchVolume": "100+",
          "started": "12h ago",
          "percentageIncrease": "50%"
        }
      ]
    },
    {
      "name": "Texas",
      "code": "TX",
      "topTopic": "sheikh hasina",
      "category": "Law and Government",
      "trendingScore": 95,
      "topics": [
        {
          "name": "sheikh hasina",
          "relevanceScore": 95,
          "category": "Law and Government",
          "searchVolume": "2K+",
          "started": "11h ago",
          "percentageIncrease": "400%"
        }
      ]
    },
    {
      "name": "Virginia",
      "code": "VA",
      "topTopic": "river north correctional center",
      "category": "Law and Government",
      "trendingScore": 100,
      "topics": [
        {
          "name": "river north correctional center",
          "relevanceScore": 100,
          "category": "Law and Government",
          "searchVolume": "2K+",
          "started": "8h ago",
          "percentageIncrease": "1000%"
        },
        {
          "name": "sheikh hasina",
          "relevanceScore": 100,
          "category": "Law and Government",
          "searchVolume": "500+",
          "started": "11h ago",
          "percentageIncrease": "700%"
        },
        {
          "name": "fema",
          "relevanceScore": 100,
          "category": "Law and Government",
          "searchVolume": "100+",
          "started": "5h ago",
          "percentageIncrease": "700%"
        },
        {
          "name": "oj simpson death",
          "relevanceScore": 95,
          "category": "Law and Government",
          "searchVolume": "100+",
          "started": "50 minutes ago",
          "trendBreakdown": "abc",
          "percentageIncrease": "400%"
        }
      ]
    },
    {
      "name": "District of Columbia",
      "code": "DC",
      "topTopic": "sheikh hasina",
      "category": "Law and Government",
      "trendingScore": 100,
      "topics": [
        {
          "name": "sheikh hasina",
          "relevanceScore": 100,
          "category": "Law and Government",
          "searchVolume": "1K+",
          "started": "11h ago",
          "percentageIncrease": "800%"
        },
        {
          "name": "lindsey halligan",
          "relevanceScore": 100,
          "category": "Law and Government",
          "searchVolume": "500+",
          "started": "5h ago",
          "percentageIncrease": "800%"
        },
        {
          "name": "fema",
          "relevanceScore": 100,
          "category": "Law and Government",
          "searchVolume": "500+",
          "started": "5h ago",
          "trendBreakdown": "david",
          "percentageIncrease": "700%"
        },
        {
          "name": "alexis wilkins",
          "relevanceScore": 95,
          "category": "Law and Government",
          "searchVolume": "100+",
          "started": "4h ago",
          "percentageIncrease": "300%"
        }
      ]
    },
    {
      "name": "Oklahoma",
      "code": "OK",
      "topTopic": "news on",
      "category": "Law and Government",
      "trendingScore": 90,
      "topics": [
        {
          "name": "news on",
          "relevanceScore": 90,
          "category": "Law and Government",
          "searchVolume": "100+",
          "started": "13h ago",
          "percentageIncrease": "100%"
        }
      ]
    },
    {
      "name": "Vermont",
      "code": "VT",
      "topTopic": "wcax weather",
      "category": "Law and Government",
      "trendingScore": 95,
      "topics": [
        {
          "name": "wcax weather",
          "relevanceScore": 95,
          "category": "Law and Government",
          "searchVolume": "100+",
          "started": "1h ago",
          "percentageIncrease": "200%"
        }
      ]
    },
    {
      "name": "Washington",
      "code": "WA",
      "topTopic": "huffington post",
      "category": "Law and Government",
      "trendingScore": 95,
      "topics": [
        {
          "name": "huffington post",
          "relevanceScore": 95,
          "category": "Law and Government",
          "searchVolume": "100+",
          "started": "9h ago",
          "percentageIncrease": "200%"
        },
        {
          "name": "oj simpson",
          "relevanceScore": 95,
          "category": "Law and Government",
          "searchVolume": "100+",
          "started": "9h ago",
          "trendBreakdown": "abc",
          "percentageIncrease": "200%"
        },
        {
          "name": "amber czech",
          "relevanceScore": 90,
          "category": "Law and Government",
          "searchVolume": "100+",
          "started": "9h ago",
          "percentageIncrease": "100%"
        }
      ]
    },
    {
      "name": "Alabama",
      "code": "AL",
      "topTopic": "news",
      "category": "Law and Government",
      "trendingScore": 85,
      "topics": [
        {
          "name": "news",
          "relevanceScore": 85,
          "category": "Law and Government",
          "searchVolume": "100+",
          "started": "12h ago",
          "percentageIncrease": "50%"
        }
      ]
    },
    {
      "name": "Kansas",
      "code": "KS",
      "topTopic": "fox news",
      "category": "Law and Government",
      "trendingScore": 85,
      "topics": [
        {
          "name": "fox news",
          "relevanceScore": 85,
          "category": "Law and Government",
          "searchVolume": "500+",
          "started": "13h ago",
          "percentageIncrease": "75%"
        }
      ]
    },
    {
      "name": "New Mexico",
      "code": "NM",
      "topTopic": "news",
      "category": "Law and Government",
      "trendingScore": 85,
      "topics": [
        {
          "name": "news",
          "relevanceScore": 85,
          "category": "Law and Government",
          "searchVolume": "100+",
          "started": "11h ago",
          "percentageIncrease": "75%"
        }
      ]
    }
  ]
}