{
  "timestamp": "2025-12-14T20:04:52.944Z",
  "states": [
    {
      "name": "Arizona",
      "code": "AZ",
      "topTopic": "bondi beach",
      "category": "Law and Government",
      "trendingScore": 100,
      "topics": [
        {
          "name": "bondi beach",
          "relevanceScore": 100,
          "category": "Law and Government",
          "searchVolume": "10K+",
          "started": "10h ago",
          "trendBreakdown": "australia",
          "percentageIncrease": "1000%"
        },
        {
          "name": "daily mail",
          "relevanceScore": 90,
          "category": "Law and Government",
          "searchVolume": "100+",
          "started": "7h ago",
          "percentageIncrease": "100%"
        }
      ]
    }
  ]
}