{
  "timestamp": "2025-12-08T14:04:46.870Z",
  "states": [
    {
      "name": "California",
      "code": "CA",
      "topTopic": "henry cuellar",
      "category": "Law and Government",
      "trendingScore": 100,
      "topics": [
        {
          "name": "henry cuellar",
          "relevanceScore": 100,
          "category": "Law and Government",
          "searchVolume": "100+",
          "started": "21h ago",
          "percentageIncrease": "500%"
        },
        {
          "name": "thailand",
          "relevanceScore": 95,
          "category": "Law and Government",
          "searchVolume": "1K+",
          "started": "10h ago",
          "percentageIncrease": "200%"
        },
        {
          "name": "monroe doctrine",
          "relevanceScore": 95,
          "category": "Law and Government",
          "searchVolume": "1K+",
          "started": "19h ago",
          "percentageIncrease": "200%"
        },
        {
          "name": "benin coup attempt",
          "relevanceScore": 95,
          "category": "Law and Government",
          "searchVolume": "1K+",
          "started": "23h ago",
          "percentageIncrease": "400%"
        },
        {
          "name": "chief",
          "relevanceScore": 95,
          "category": "Law and Government",
          "searchVolume": "100+",
          "started": "9h ago",
          "percentageIncrease": "200%"
        },
        {
          "name": "trinity poague",
          "relevanceScore": 90,
          "category": "Law and Government",
          "searchVolume": "500+",
          "started": "23h ago",
          "percentageIncrease": "100%"
        },
        {
          "name": "alberto rangel",
          "relevanceScore": 90,
          "category": "Law and Government",
          "searchVolume": "100+",
          "started": "7h ago",
          "percentageIncrease": "100%"
        },
        {
          "name": "derek chauvin",
          "relevanceScore": 90,
          "category": "Law and Government",
          "searchVolume": "100+",
          "started": "8h ago",
          "percentageIncrease": "100%"
        },
        {
          "name": "univision",
          "relevanceScore": 90,
          "category": "Law and Government",
          "searchVolume": "100+",
          "started": "12h ago",
          "percentageIncrease": "100%"
        }
      ]
    }
  ]
}