{
  "timestamp": "2025-12-18T06:04:38.527Z",
  "states": [
    {
      "name": "Connecticut",
      "code": "CT",
      "topTopic": "trump",
      "category": "Law and Government",
      "trendingScore": 100,
      "topics": [
        {
          "name": "trump",
          "relevanceScore": 100,
          "category": "Law and Government",
          "searchVolume": "2K+",
          "started": "5h ago",
          "percentageIncrease": "500%"
        },
        {
          "name": "dan bongino",
          "relevanceScore": 100,
          "category": "Law and Government",
          "searchVolume": "500+",
          "started": "7h ago",
          "percentageIncrease": "800%"
        }
      ]
    }
  ]
}