{
  "timestamp": "2025-12-13T02:33:32.196Z",
  "states": [
    {
      "name": "District of Columbia",
      "code": "DC",
      "topTopic": "dc squatter",
      "category": "Law and Government",
      "trendingScore": 100,
      "topics": [
        {
          "name": "dc squatter",
          "relevanceScore": 100,
          "category": "Law and Government",
          "searchVolume": "100+",
          "started": "2h ago",
          "percentageIncrease": "600%"
        },
        {
          "name": "attorney general letitia james",
          "relevanceScore": 95,
          "category": "Law and Government",
          "searchVolume": "100+",
          "started": "8h ago",
          "percentageIncrease": "400%"
        },
        {
          "name": "kyle rittenhouse",
          "relevanceScore": 85,
          "category": "Law and Government",
          "searchVolume": "100+",
          "started": "16h ago",
          "percentageIncrease": "75%"
        }
      ]
    }
  ]
}