{
  "timestamp": "2025-12-14T04:16:44.892Z",
  "states": [
    {
      "name": "Georgia",
      "code": "GA",
      "topTopic": "conduent",
      "category": "Law and Government",
      "trendingScore": 100,
      "topics": [
        {
          "name": "conduent",
          "relevanceScore": 100,
          "category": "Law and Government",
          "searchVolume": "500+",
          "started": "15h ago",
          "percentageIncrease": "900%"
        },
        {
          "name": "depot",
          "relevanceScore": 100,
          "category": "Law and Government",
          "searchVolume": "500+",
          "started": "15h ago",
          "percentageIncrease": "700%"
        },
        {
          "name": "post office",
          "relevanceScore": 90,
          "category": "Law and Government",
          "searchVolume": "100+",
          "started": "11h ago",
          "percentageIncrease": "100%"
        }
      ]
    }
  ]
}