{
  "timestamp": "2025-12-15T10:05:21.665Z",
  "states": [
    {
      "name": "Louisiana",
      "code": "LA",
      "topTopic": "benjamin erickson",
      "category": "Law and Government",
      "trendingScore": 100,
      "topics": [
        {
          "name": "benjamin erickson",
          "relevanceScore": 100,
          "category": "Law and Government",
          "searchVolume": "1K+",
          "started": "11h ago",
          "trendBreakdown": "brown",
          "percentageIncrease": "1000%"
        },
        {
          "name": "pecanland mall",
          "relevanceScore": 100,
          "category": "Law and Government",
          "searchVolume": "100+",
          "started": "8h ago",
          "percentageIncrease": "500%"
        },
        {
          "name": "cnn",
          "relevanceScore": 95,
          "category": "Law and Government",
          "searchVolume": "100+",
          "started": "5h ago",
          "percentageIncrease": "300%"
        }
      ]
    }
  ]
}