{
  "timestamp": "2025-12-12T12:04:48.685Z",
  "states": [
    {
      "name": "Michigan",
      "code": "MI",
      "topTopic": "tyler robinson",
      "category": "Law and Government",
      "trendingScore": 100,
      "topics": [
        {
          "name": "tyler robinson",
          "relevanceScore": 100,
          "category": "Law and Government",
          "searchVolume": "500+",
          "started": "13h ago",
          "percentageIncrease": "600%"
        },
        {
          "name": "kristi noem",
          "relevanceScore": 95,
          "category": "Law and Government",
          "searchVolume": "100+",
          "started": "7h ago",
          "percentageIncrease": "200%"
        }
      ]
    }
  ]
}