{
  "timestamp": "2025-12-16T22:04:33.491Z",
  "states": [
    {
      "name": "Nebraska",
      "code": "NE",
      "topTopic": "westroads mall",
      "category": "Law and Government",
      "trendingScore": 95,
      "topics": [
        {
          "name": "westroads mall",
          "relevanceScore": 95,
          "category": "Law and Government",
          "searchVolume": "500+",
          "started": "23h ago",
          "trendBreakdown": "omaha",
          "percentageIncrease": "300%"
        }
      ]
    }
  ]
}