{
  "timestamp": "2025-12-24T16:04:34.828Z",
  "states": [
    {
      "name": "New Jersey",
      "code": "NJ",
      "topTopic": "silver lake nursing home",
      "category": "Law and Government",
      "trendingScore": 100,
      "topics": [
        {
          "name": "silver lake nursing home",
          "relevanceScore": 100,
          "category": "Law and Government",
          "searchVolume": "5K+",
          "started": "20h ago",
          "trendBreakdown": "nursing",
          "percentageIncrease": "1000%"
        },
        {
          "name": "melodee buzzard",
          "relevanceScore": 100,
          "category": "Law and Government",
          "searchVolume": "1K+",
          "started": "19h ago",
          "trendBreakdown": "ashlee",
          "percentageIncrease": "500%"
        },
        {
          "name": "lillian bonsignore",
          "relevanceScore": 100,
          "category": "Law and Government",
          "searchVolume": "500+",
          "started": "19h ago",
          "percentageIncrease": "700%"
        },
        {
          "name": "delaware state police",
          "relevanceScore": 100,
          "category": "Law and Government",
          "searchVolume": "500+",
          "started": "16h ago",
          "trendBreakdown": "delaware",
          "percentageIncrease": "500%"
        },
        {
          "name": "garden state plaza",
          "relevanceScore": 90,
          "category": "Law and Government",
          "searchVolume": "500+",
          "started": "15h ago",
          "percentageIncrease": "100%"
        }
      ]
    }
  ]
}