{
  "timestamp": "2026-01-02T02:39:32.752Z",
  "states": [
    {
      "name": "New Jersey",
      "code": "NJ",
      "topTopic": "holland america cruise ship",
      "category": "Law and Government",
      "trendingScore": 100,
      "topics": [
        {
          "name": "holland america cruise ship",
          "relevanceScore": 100,
          "category": "Law and Government",
          "searchVolume": "500+",
          "started": "3h ago",
          "percentageIncrease": "1000%"
        },
        {
          "name": "learning center",
          "relevanceScore": 100,
          "category": "Law and Government",
          "searchVolume": "100+",
          "started": "21h ago",
          "percentageIncrease": "1000%"
        },
        {
          "name": "garden state plaza",
          "relevanceScore": 95,
          "category": "Law and Government",
          "searchVolume": "1K+",
          "started": "12h ago",
          "trendBreakdown": "garden",
          "percentageIncrease": "200%"
        },
        {
          "name": "nbc news",
          "relevanceScore": 95,
          "category": "Law and Government",
          "searchVolume": "100+",
          "started": "21h ago",
          "percentageIncrease": "300%"
        },
        {
          "name": "american dream mall",
          "relevanceScore": 90,
          "category": "Law and Government",
          "searchVolume": "2K+",
          "started": "11h ago",
          "percentageIncrease": "100%"
        },
        {
          "name": "nj minimum wage",
          "relevanceScore": 90,
          "category": "Law and Government",
          "searchVolume": "100+",
          "started": "2h ago",
          "percentageIncrease": "100%"
        }
      ]
    }
  ]
}