{
  "timestamp": "2025-12-23T18:04:58.283Z",
  "states": [
    {
      "name": "Tennessee",
      "code": "TN",
      "topTopic": "are banks open on christmas eve",
      "category": "Law and Government",
      "trendingScore": 95,
      "topics": [
        {
          "name": "are banks open on christmas eve",
          "relevanceScore": 95,
          "category": "Law and Government",
          "searchVolume": "100+",
          "started": "3h ago",
          "trendBreakdown": "christmas",
          "percentageIncrease": "300%"
        }
      ]
    }
  ]
}