{
  "timestamp": "2026-01-01T04:22:23.112Z",
  "states": [
    {
      "name": "Texas",
      "code": "TX",
      "topTopic": "ut",
      "category": "Law and Government",
      "trendingScore": 95,
      "topics": [
        {
          "name": "ut",
          "relevanceScore": 95,
          "category": "Law and Government",
          "searchVolume": "1K+",
          "started": "8h ago",
          "percentageIncrease": "400%"
        },
        {
          "name": "alberto prieto",
          "relevanceScore": 95,
          "category": "Law and Government",
          "searchVolume": "2K+",
          "started": "15h ago",
          "percentageIncrease": "400%"
        },
        {
          "name": "kansas city international airport",
          "relevanceScore": 95,
          "category": "Law and Government",
          "searchVolume": "500+",
          "started": "7h ago",
          "percentageIncrease": "300%"
        },
        {
          "name": "prince",
          "relevanceScore": 95,
          "category": "Law and Government",
          "searchVolume": "100+",
          "started": "1h ago",
          "percentageIncrease": "200%"
        },
        {
          "name": "bank",
          "relevanceScore": 95,
          "category": "Law and Government",
          "searchVolume": "100+",
          "started": "19h ago",
          "percentageIncrease": "300%"
        }
      ]
    }
  ]
}