{
  "timestamp": "2025-12-16T08:05:03.403Z",
  "states": [
    {
      "name": "Texas",
      "code": "TX",
      "topTopic": "brian walshe",
      "category": "Law and Government",
      "trendingScore": 100,
      "topics": [
        {
          "name": "brian walshe",
          "relevanceScore": 100,
          "category": "Law and Government",
          "searchVolume": "2K+",
          "started": "15h ago",
          "percentageIncrease": "500%"
        },
        {
          "name": "daily mail",
          "relevanceScore": 85,
          "category": "Law and Government",
          "searchVolume": "100+",
          "started": "19h ago",
          "percentageIncrease": "50%"
        }
      ]
    }
  ]
}